<?xml version="1.0" encoding="utf-8"?>
<LanguageData>
  <!--The following translations were generated by https://www.deepl.com/-->
  <!-- EN: Unethical -->
  <QE_CloningAbhorrent.label>不道德</QE_CloningAbhorrent.label>
  <!-- EN: Bringing new life into this world in a test tube is horrid, downright unethical. -->
  <QE_CloningAbhorrent.description>用试管将新生命带入这个世界是可怕的，简直是不道德的。</QE_CloningAbhorrent.description>
  <!-- EN: Approved -->
  <QE_CloningApproved.label>已批准</QE_CloningApproved.label>
  <!-- EN: Cloning is a velnerable task, bringing forth a new generation with great ease. -->
  <QE_CloningApproved.description>克隆是一项艰巨的任务，可以轻而易举地创造出新的一代。</QE_CloningApproved.description>
  <!-- EN: Neutral -->
  <QE_CloningNeutral.label>中性</QE_CloningNeutral.label>
  <!-- EN: Cloning is what it is. It is neither good, nor evil. -->
  <QE_CloningNeutral.description>克隆就是克隆。它既不是善，也不是恶。</QE_CloningNeutral.description>
</LanguageData>
